README.rst
setup.py
PyUrbanDict.egg-info/PKG-INFO
PyUrbanDict.egg-info/SOURCES.txt
PyUrbanDict.egg-info/dependency_links.txt
PyUrbanDict.egg-info/requires.txt
PyUrbanDict.egg-info/top_level.txt
PyUrbanDict.egg-info/zip-safe
pyurbandict/__init__.py
pyurbandict/exception.py
pyurbandict/main.py